compress_comics_TheHardew/__init__.py
compress_comics_TheHardew/argument_parser.py
compress_comics_TheHardew/comic_compressor.py
compress_comics_TheHardew/compress_comics.py
compress_comics_TheHardew/text_bar.py
compress_comics_thehardew-0.4.12.dist-info/METADATA
compress_comics_thehardew-0.4.12.dist-info/WHEEL
compress_comics_thehardew-0.4.12.dist-info/entry_points.txt
compress_comics_thehardew-0.4.12.dist-info/licenses/LICENSE
compress_comics_thehardew-0.4.12.dist-info/RECORD
