Metadata-Version: 2.1
Name: compress_comics_TheHardew
Version: 0.4.12
Summary: Compress images in cbz/cbr files with jpegxl, fast.
Project-URL: Homepage, https://github.com/TheHardew/compress_comics
Project-URL: Issues, https://github.com/TheHardew/compress_comics/issues
Author: TheHardew
License-File: LICENSE
Classifier: License :: OSI Approved :: The Unlicense (Unlicense)
Classifier: Operating System :: OS Independent
Classifier: Programming Language :: Python :: 3
Requires-Python: >=3.11
Requires-Dist: patool
Requires-Dist: tqdm
